[
  {
    "slug": "motion-activated-rv-step-lights-fall-camping-safety",
    "title": "Why Fall RV Trips Are Going Dark Without These Motion-Activated Step Lights – Glow Up Your Safety Game",
    "excerpt": "Don't let fall RV trips go dark! Discover the 7 best motion-activated step lights under $30 on Amazon for 2025—tested, affordable, and perfect for nighttime safety.",
    "featuredImage": "/images/discovery/rv-step-lights-fall.png",
    "type": "list",
    "tags": ["safety", "lighting", "fall-camping", "amazon-deals", "rv-accessories", "budget-friendly"],
    "publishDate": "2025-01-08",
    "readTime": 8,
    "trendingScore": 98,
    "content": [
      {
        "type": "paragraph",
        "text": "As the leaves turn gold and the sun sets before dinner, something changes on every fall camping trip: your RV steps disappear into the shadows. What was a simple hop down in July becomes a risky stumble in October—especially on uneven ground or dew-slicked campsites."
      },
      {
        "type": "paragraph",
        "text": "With the 2025 Fall Detroit RV Show just around the corner (October 1!) and safety recalls making headlines, it's time to take nighttime visibility seriously. The good news? You don't need expensive wiring or tools. For under $30, a set of motion-activated LED step lights can transform your RV into a safer, smarter home on wheels."
      },
      {
        "type": "paragraph",
        "text": "After testing dozens of options and reading hundreds of real camper reviews, I've narrowed it down to the 7 best motion-activated RV step lights on Amazon for 2025—all under $30, battery-powered (or rechargeable), and ready to stick on in minutes."
      },
      {
        "type": "heading",
        "text": "Why Motion-Activated Lights Are a Fall Camping Must-Have"
      },
      {
        "type": "paragraph",
        "text": "Let's be real: nobody plans to trip. But it happens—especially when you're half-asleep grabbing firewood at 11 p.m. or your kids are running to the bathroom in the dark."
      },
      {
        "type": "paragraph",
        "text": "These little lights solve that problem with smart, hands-free illumination:"
      },
      {
        "type": "list",
        "items": [
          "✅ Turn on only when you approach (no wasted battery)",
          "✅ Mount in seconds with magnets or strong adhesive",
          "✅ Work in rain, cold, and dust (most are weather-resistant)",
          "✅ Cost less than a tank of gas—but prevent injuries that cost way more"
        ]
      },
      {
        "type": "heading",
        "text": "Top 7 Motion-Activated RV Step Lights Under $30 (Amazon 2025)"
      },
      {
        "type": "heading",
        "text": "1. CCBASEBALL Motion-Activated RV Step Lights – Best Overall Value"
      },
      {
        "type": "product",
        "name": "CCBASEBALL Motion-Activated RV Step Lights",
        "price": "$13.59",
        "amazonLink": "https://amzn.to/4pSgU3I"
      },
      {
        "type": "paragraph",
        "text": "Price: $13.59 for 2-pack | Why we love it: Super bright 10-LED strips with a 10-foot motion range and 18-second auto-off. The magnetic + adhesive combo sticks to any RV surface—even curved steps."
      },
      {
        "type": "paragraph",
        "text": "Thousands of campers swear by these for weekend trips. Just pop in 4 AAA batteries (not included), and you're set for weeks."
      },
      {
        "type": "heading",
        "text": "2. Fymblin 3-Pack Motion Sensor Lights – Best for Full Coverage"
      },
      {
        "type": "product",
        "name": "Fymblin 3-Pack Motion Sensor Lights",
        "price": "$14.99",
        "amazonLink": "https://amzn.to/3IWAlYs"
      },
      {
        "type": "paragraph",
        "text": "Price: $14.99 for 3 lights | Why we love it: Get three lights for less than $5 each! Perfect for lighting your step and the ground in front of it. Same 10-LED brightness and reliable PIR sensor as pricier brands."
      },
      {
        "type": "paragraph",
        "text": "Ideally, mount one on the step, one on the trailer frame, and one near your door for a safe path."
      },
      {
        "type": "heading",
        "text": "3. EZVALO Rechargeable Step Lights – Best for No-Battery Hassle"
      },
      {
        "type": "product",
        "name": "EZVALO Rechargeable Step Lights",
        "price": "$17.99",
        "amazonLink": "https://amzn.to/3VWcNpK"
      },
      {
        "type": "paragraph",
        "text": "Price: $17.99 for 2-pack | Why we love it: Ditch disposable batteries forever! These USB-rechargeable lights last up to 45 days on a single charge and let you choose between warm, natural, or cool white light."
      },
      {
        "type": "paragraph",
        "text": "Great if you hate buying AAA batteries or want a cleaner setup. Just remember: the magnet isn't as strong—so use the included tape on bumpy roads."
      },
      {
        "type": "heading",
        "text": "4. LYCARESUN 3-Pack LED Step Lights – Brightest Budget Pick"
      },
      {
        "type": "product",
        "name": "LYCARESUN 3-Pack LED Step Lights",
        "price": "$19.99",
        "amazonLink": "https://amzn.to/434BN1J"
      },
      {
        "type": "paragraph",
        "text": "Price: $19.99 for 3 | Why we love it: 50 lumens of crisp white light that cuts through fog and rain. The wide 120° sensor means it sees you coming from any angle."
      },
      {
        "type": "paragraph",
        "text": "A solid choice if your campsite has zero ambient light."
      },
      {
        "type": "heading",
        "text": "5. EJYTRVT Motion Sensor Lights – Reliable & Simple"
      },
      {
        "type": "product",
        "name": "EJYTRVT Motion Sensor Lights",
        "price": "$18.99",
        "amazonLink": "https://amzn.to/46S9lmp"
      },
      {
        "type": "paragraph",
        "text": "Price: $18.99 for 3 | Why we love it: No-frills, dependable performance. Easy to install, consistent activation, and great for older RVs with metal steps."
      },
      {
        "type": "paragraph",
        "text": "Not the brightest, but more than enough for safe footing."
      },
      {
        "type": "heading",
        "text": "6. Guankai 8-Pack Stair Lights – Best for Large Trailers"
      },
      {
        "type": "product",
        "name": "Guankai 8-Pack Stair Lights",
        "price": "$19.99",
        "amazonLink": "https://amzn.to/4h1zzG8"
      },
      {
        "type": "paragraph",
        "text": "Price: $19.99 for 8 lights! | Why we love it: Need to light a whole staircase or a long trailer entry? This pack gives you serious coverage for under $2.50 per light."
      },
      {
        "type": "paragraph",
        "text": "Perfect for toy haulers or fifth wheels with multiple steps."
      },
      {
        "type": "heading",
        "text": "7. innofox 6-Pack Stick-On Lights – Best for Quick Setup"
      },
      {
        "type": "product",
        "name": "innofox 6-Pack Stick-On Lights",
        "price": "$15.99",
        "amazonLink": "https://amzn.to/4gZ35MN"
      },
      {
        "type": "paragraph",
        "text": "Price: $15.99 for 6 | Why we love it: Ultra-thin, lightweight, and sticks anywhere with 3M tape. Great for renters or pop-up campers where magnets won't work."
      },
      {
        "type": "paragraph",
        "text": "Thousands of 5-star reviews from real campers say: 'Wish I'd bought these years ago!'"
      },
      {
        "type": "heading",
        "text": "Pro Tips for Installation & Longevity"
      },
      {
        "type": "list",
        "items": [
          "Clean the surface first. Wipe with alcohol before sticking—dirt kills adhesion.",
          "Angle the light downward. Point it at your feet, not the sky, to avoid glare.",
          "Use both magnet + tape. Even if it sticks with magnets, add tape for bumpy roads.",
          "Test before your trip. Do a nighttime walk-around at home to adjust placement."
        ]
      },
      {
        "type": "heading",
        "text": "Final Verdict: Don't Wait for a Fall to Upgrade"
      },
      {
        "type": "paragraph",
        "text": "For less than the cost of a campfire pizza kit, you can eliminate one of the most common (and preventable) RV injuries. Whether you choose the CCBASEBALL for simplicity, Fymblin for coverage, or EZVALO for rechargeable convenience, you're making your fall adventures safer and smoother."
      },
      {
        "type": "paragraph",
        "text": "And with the 2025 RV season heating up, now's the perfect time to grab yours before the next chilly, moonless night rolls in."
      }
    ]
  }
]

